Mundo01/__init__.py
Mundo01/Exercicios/__init__.py
Mundo01/Exercicios/ex001.py
Mundo01/Exercicios/ex002.py
Mundo01/Exercicios/ex003.py
Mundo01/Exercicios/ex004.py
Mundo01/Exercicios/ex005.py
Mundo01/Exercicios/ex006.py
Mundo01/Exercicios/ex007.py
Mundo01/Exercicios/ex008.py
Mundo01/Exercicios/ex009.py
Mundo01/Exercicios/ex010.py
Mundo01/Exercicios/ex011.py
Mundo01/Exercicios/ex012.py
Mundo01/Exercicios/ex013.py
Mundo01/Exercicios/ex014.py
Mundo01/Exercicios/ex015.py
Mundo01/Exercicios/ex016.py
Mundo01/Exercicios/ex017.py
Mundo01/Exercicios/ex018.py
Mundo01/Exercicios/ex019.py
Mundo01/Exercicios/ex020.py
Mundo01/Exercicios/ex021.py
Mundo01/Exercicios/ex022.py
Mundo01/Exercicios/ex023.py
Mundo01/Exercicios/ex024.py
Mundo01/Exercicios/ex025.py
Mundo01/Exercicios/ex026.py
Mundo01/Exercicios/ex027.py
Mundo01/Exercicios/ex028.py
Mundo01/Exercicios/ex029.py
Mundo01/Exercicios/ex030.py
Mundo01/Exercicios/ex031.py
Mundo01/Exercicios/ex032.py
Mundo01/Exercicios/ex033.py
Mundo01/Exercicios/ex034.py
Mundo01/Exercicios/ex035.py
meu_pacote_python-1.0.7.dist-info/licenses/LICENSE
meu_pacote_python-1.0.7.dist-info/METADATA
meu_pacote_python-1.0.7.dist-info/WHEEL
meu_pacote_python-1.0.7.dist-info/entry_points.txt
meu_pacote_python-1.0.7.dist-info/top_level.txt
meu_pacote_python-1.0.7.dist-info/RECORD
