Metadata-Version: 2.4
Name: meu_pacote_python
Version: 1.0.7
Summary: Exercícios de Python - Curso em Vídeo
Home-page: https://github.com/igorpompeo/Python
Author: Igor Pompeo
Author-email: pompbass@gmail.com
License: MIT
Classifier: Programming Language :: Python :: 3
Classifier: License :: OSI Approved :: MIT License
Classifier: Operating System :: OS Independent
Requires-Python: >=3.8
License-File: LICENSE
Requires-Dist: colorama>=0.4.0
Requires-Dist: emoji>=2.0.0
Provides-Extra: games
Requires-Dist: pygame>=2.0.0; extra == "games"
Provides-Extra: dev
Requires-Dist: flake8; extra == "dev"
Requires-Dist: black; extra == "dev"
Requires-Dist: pytest; extra == "dev"
Requires-Dist: coverage; extra == "dev"
Dynamic: author
Dynamic: author-email
Dynamic: classifier
Dynamic: description
Dynamic: description-content-type
Dynamic: home-page
Dynamic: license-file
Dynamic: provides-extra
Dynamic: requires-dist
Dynamic: requires-python
Dynamic: summary
